obzerveai/__init__.py
obzerveai/main.py
obzerveai/sanitize.py
obzerveai-0.0.5.dist-info/LICENSE.txt
obzerveai-0.0.5.dist-info/METADATA
obzerveai-0.0.5.dist-info/WHEEL
obzerveai-0.0.5.dist-info/top_level.txt
obzerveai-0.0.5.dist-info/RECORD
