Metadata-Version: 2.1
Name: obzerveai
Version: 0.0.5
Summary: A python package of utilities for AI based solutions
Author-email: obzerveai <goyal.siddharth22@gmail.com>
Project-URL: Homepage, https://github.com/obzerveai/
Classifier: Programming Language :: Python :: 3
Classifier: Operating System :: OS Independent
Requires-Python: >=3.8
License-File: LICENSE.txt
Requires-Dist: influxdb-client ==1.41.0
